poweretl/databricks/__init__.py
poweretl/databricks/model/DatabricksMetaProvider.py
poweretl/databricks/model/__init__.py
poweretl/databricks/model/sql/01.meta_model.sql
poweretl/databricks/model/sql/02.init_data.sql
poweretl_databricks-0.0.1a1.dist-info/METADATA
poweretl_databricks-0.0.1a1.dist-info/WHEEL
poweretl_databricks-0.0.1a1.dist-info/RECORD
