Metadata-Version: 2.4
Name: poweretl-databricks
Version: 0.0.1a1
Summary: 
Author: Your Name
Author-email: you@example.com
Requires-Python: >=3.13
Classifier: Programming Language :: Python :: 3
Classifier: Programming Language :: Python :: 3.13
Classifier: Programming Language :: Python :: 3.14
Requires-Dist: poweretl-common
